tpkutils/__init__.py
tpkutils/cli.py
tpkutils/preview_template.html
tpkutils/util.py
tpkutils-0.8.2.dist-info/entry_points.txt
tpkutils-0.8.2.dist-info/LICENSE.md
tpkutils-0.8.2.dist-info/WHEEL
tpkutils-0.8.2.dist-info/METADATA
tpkutils-0.8.2.dist-info/RECORD
