Metadata-Version: 2.1
Name: tpkutils
Version: 0.8.2
Summary: ArcGIS Tile Package Utilities
License: ISC
Author: Brendan Ward
Author-email: bcward@astutespruce.com
Requires-Python: >=3.7,<4.0
Classifier: License :: OSI Approved
Classifier: License :: OSI Approved :: ISC License (ISCL)
Classifier: Programming Language :: Python :: 3
Classifier: Programming Language :: Python :: 3.10
Classifier: Programming Language :: Python :: 3.7
Classifier: Programming Language :: Python :: 3.8
Classifier: Programming Language :: Python :: 3.9
Requires-Dist: click (>=8.1.3,<9.0.0)
Requires-Dist: mercantile (>=1.2.1,<2.0.0)
Requires-Dist: pymbtiles (>=0.5.0,<0.6.0)
Requires-Dist: six (>=1.16.0,<2.0.0)
